pyqalx/__init__.py
pyqalx/__version__.py
pyqalx/bot/__init__.py
pyqalx/config/__init__.py
pyqalx/config/configs.py
pyqalx/config/defaults/__init__.py
pyqalx/config/defaults/bots.py
pyqalx/config/types.py
pyqalx/core/__init__.py
pyqalx/core/adapters/__init__.py
pyqalx/core/adapters/adapter.py
pyqalx/core/adapters/blueprint.py
pyqalx/core/adapters/bot.py
pyqalx/core/adapters/factory.py
pyqalx/core/adapters/group.py
pyqalx/core/adapters/item.py
pyqalx/core/adapters/notification.py
pyqalx/core/adapters/queue.py
pyqalx/core/adapters/set.py
pyqalx/core/adapters/worker.py
pyqalx/core/encryption.py
pyqalx/core/entities/__init__.py
pyqalx/core/entities/blueprint.py
pyqalx/core/entities/bot.py
pyqalx/core/entities/entity.py
pyqalx/core/entities/factory.py
pyqalx/core/entities/group.py
pyqalx/core/entities/item.py
pyqalx/core/entities/notification.py
pyqalx/core/entities/queue.py
pyqalx/core/entities/set.py
pyqalx/core/entities/worker.py
pyqalx/core/enums.py
pyqalx/core/errors.py
pyqalx/core/log.py
pyqalx/core/registry.py
pyqalx/core/session.py
pyqalx/core/signals.py
pyqalx/core/tags.py
pyqalx/core/utils.py
pyqalx/factories/__init__.py
pyqalx/factories/bot_sources.py
pyqalx/factories/debug.py
pyqalx/factories/factory.py
pyqalx/factories/mixins.py
pyqalx/factories/sectors/__init__.py
pyqalx/factories/sectors/manager.py
pyqalx/factories/sectors/providers/__init__.py
pyqalx/factories/sectors/providers/aws/__init__.py
pyqalx/factories/sectors/providers/aws/provider.py
pyqalx/factories/sectors/providers/aws/stack.py
pyqalx/factories/sectors/providers/local/__init__.py
pyqalx/factories/sectors/providers/local/provider.py
pyqalx/factories/sectors/providers/provider.py
pyqalx/factories/sectors/sectors.py
pyqalx/factories/tree.py
pyqalx/transport/__init__.py
pyqalx/transport/api.py
pyqalx/transport/core.py
pyqalx/vendor/__init__.py
qalxcli/__init__.py
qalxcli/cli/__init__.py
qalxcli/cli/bots.py
qalxcli/cli/factory.py
qalxcli/cli/qalx.py
qalxcli/cli_types.py
qalxcli/utils.py
pyqalx-0.19.2.dist-info/LICENCE.txt
pyqalx-0.19.2.dist-info/METADATA
pyqalx-0.19.2.dist-info/WHEEL
pyqalx-0.19.2.dist-info/entry_points.txt
pyqalx-0.19.2.dist-info/RECORD
