Metadata-Version: 2.1
Name: pyqalx
Version: 0.19.2
Summary: High-level interfaces to the qalx API
Home-page: https://qalx.net
License: GPL-3.0
Keywords: qalx,engineering,simulation
Author: AgileTek Engineering Limited
Author-email: london@agiletek.co.uk
Requires-Python: >=3.8,<4.0
Classifier: Development Status :: 4 - Beta
Classifier: Intended Audience :: Manufacturing
Classifier: Intended Audience :: Science/Research
Classifier: Intended Audience :: Telecommunications Industry
Classifier: License :: OSI Approved :: GNU General Public License v3 (GPLv3)
Classifier: License :: OSI Approved :: GNU General Public License v3 or later (GPLv3+)
Classifier: Natural Language :: English
Classifier: Operating System :: OS Independent
Classifier: Programming Language :: Python :: 3
Classifier: Programming Language :: Python :: 3.8
Classifier: Programming Language :: Python :: 3.9
Classifier: Programming Language :: Python :: 3.10
Classifier: Programming Language :: Python :: 3.11
Classifier: Programming Language :: Python :: 3.12
Provides-Extra: flaky
Provides-Extra: pip-licenses
Provides-Extra: sphinx
Requires-Dist: addict (>=2.4,<3.0)
Requires-Dist: appdirs (>=1.4,<2.0)
Requires-Dist: boto3 (>=1.34,<2.0)
Requires-Dist: bson-extra (>=0.0.4,<0.0.5)
Requires-Dist: click (>=8.0,<9.0)
Requires-Dist: colorama (>=0.4.3,<0.5.0)
Requires-Dist: cryptography (>=42.0,<43.0)
Requires-Dist: deprecation (>=2.0,<3.0)
Requires-Dist: dill (>=0.3.3)
Requires-Dist: flaky (>=3.7,<4.0) ; extra == "flaky"
Requires-Dist: gitpython (>=3.1,<4.0)
Requires-Dist: jsonschema (>=4.21,<5.0)
Requires-Dist: pip-licenses (>=4.3,<5.0) ; extra == "pip-licenses"
Requires-Dist: pyyaml (==5.3.1)
Requires-Dist: requests (>=2.21,<3.0)
Requires-Dist: sphinx (<7.2) ; extra == "sphinx"
Requires-Dist: tabulate (>=0.9,<0.10)
Requires-Dist: treelib (>=1.6,<2.0)
Requires-Dist: troposphere (>=4.7,<5.0)
Project-URL: Documentation, https://docs.qalx.net
